{
  "name": "__EAnimToolBlendOperation",
  "isEnum": true,
  "properties": {
    "Tween": [
      "EAnimToolBlendOperation"
    ],
    "BlendToNeighbor": [
      "EAnimToolBlendOperation"
    ],
    "PushPull": [
      "EAnimToolBlendOperation"
    ],
    "BlendRelative": [
      "EAnimToolBlendOperation"
    ],
    "BlendToEase": [
      "EAnimToolBlendOperation"
    ],
    "SmoothRough": [
      "EAnimToolBlendOperation"
    ],
    "EAnimToolBlendOperation_MAX": [
      "EAnimToolBlendOperation"
    ]
  },
  "methods": []
}