{
  "name": "__EditorPrompt",
  "properties": {},
  "methods": [
    {
      "name": "ShowPromptForStruct",
      "return": "bool",
      "args": [
        {
          "name": "Struct",
          "type": "?"
        }
      ]
    },
    {
      "name": "ShowPromptForStruct",
      "return": "bool",
      "args": [
        {
          "name": "Struct",
          "type": "?"
        },
        {
          "name": "Options",
          "type": "FScriptEditorPromptOptions"
        }
      ]
    },
    {
      "name": "ShowPromptToCallFunction",
      "return": "bool",
      "args": [
        {
          "name": "Object",
          "type": "UObject"
        },
        {
          "name": "FunctionName",
          "type": "FName"
        }
      ]
    },
    {
      "name": "ShowPromptToCallFunction",
      "return": "bool",
      "args": [
        {
          "name": "Object",
          "type": "UObject"
        },
        {
          "name": "FunctionName",
          "type": "FName"
        },
        {
          "name": "Options",
          "type": "FScriptEditorPromptOptions"
        }
      ]
    },
    {
      "name": "ShowPromptToCallFunction",
      "return": "bool",
      "args": [
        {
          "name": "Object",
          "type": "UObject"
        },
        {
          "name": "FunctionName",
          "type": "FName"
        },
        {
          "name": "Options",
          "type": "FScriptEditorPromptOptions"
        },
        {
          "name": "FirstParameterObjects",
          "type": "TArray<UObject>"
        }
      ]
    },
    {
      "name": "ShowPromptToCallFunctionOnObjects",
      "return": "bool",
      "args": [
        {
          "name": "Objects",
          "type": "TArray<UObject>"
        },
        {
          "name": "FunctionName",
          "type": "FName"
        },
        {
          "name": "Options",
          "type": "FScriptEditorPromptOptions"
        }
      ]
    }
  ]
}