{
  "name": "__EFieldFalloffType",
  "isEnum": true,
  "properties": {
    "Field_FallOff_None": [
      "EFieldFalloffType",
      "No falloff function is used"
    ],
    "Field_Falloff_Linear": [
      "EFieldFalloffType",
      "The falloff function will be proportional to x"
    ],
    "Field_Falloff_Inverse": [
      "EFieldFalloffType",
      "The falloff function will be proportional to 1.0/x"
    ],
    "Field_Falloff_Squared": [
      "EFieldFalloffType",
      "The falloff function will be proportional to x*x"
    ],
    "Field_Falloff_Logarithmic": [
      "EFieldFalloffType",
      "The falloff function will be proportional to log(x)"
    ],
    "Field_Falloff_Max": [
      "EFieldFalloffType",
      "//256th entry"
    ]
  },
  "methods": []
}