{
  "name": "__ENiagaraRandomnessMode",
  "isEnum": true,
  "doc": "Toggles the behavior of the random number generator.",
  "properties": {
    "NewEnumerator0": [
      "ENiagaraRandomnessMode",
      "The random number generator will use the global mode toggled on a per-emitter basis."
    ],
    "NewEnumerator1": [
      "ENiagaraRandomnessMode",
      "The random number generator will produce deterministic random numbers."
    ],
    "NewEnumerator2": [
      "ENiagaraRandomnessMode",
      "The random number generator will produce non-deterministic random numbers."
    ],
    "ENiagaraRandomnessMode_MAX": [
      "ENiagaraRandomnessMode"
    ]
  },
  "methods": []
}