{
  "name": "__EOffsetJoinMethod",
  "isEnum": true,
  "properties": {
    "Square": [
      "EOffsetJoinMethod",
      "Cut off corners between offset edges with square shapes"
    ],
    "Miter": [
      "EOffsetJoinMethod",
      "Miter corners between offset edges, extending the neighboring curve edges straight to their intersection point, unless that point is farther than the miter limit distance"
    ],
    "Round": [
      "EOffsetJoinMethod",
      "Smoothly join corners between offset edges with circular paths"
    ],
    "EOffsetJoinMethod_MAX": [
      "EOffsetJoinMethod"
    ]
  },
  "methods": []
}