{
  "name": "FAnchors",
  "isStruct": true,
  "doc": "Describes how a widget is anchored.",
  "properties": {
    "Minimum": [
      "FVector2D",
      "Holds the minimum anchors, left + top."
    ],
    "Maximum": [
      "FVector2D",
      "Holds the maximum anchors, right + bottom."
    ]
  },
  "methods": [
    {
      "name": "opEquals",
      "return": "bool",
      "const": true,
      "args": [
        {
          "name": "Other",
          "type": "FAnchors"
        }
      ]
    },
    {
      "name": "IsStretchedVertical",
      "return": "bool",
      "const": true,
      "args": []
    },
    {
      "name": "IsStretchedHorizontal",
      "return": "bool",
      "const": true,
      "args": []
    },
    {
      "name": "opAssign",
      "return": "FAnchors&",
      "args": [
        {
          "name": "Other",
          "type": "FAnchors"
        }
      ]
    }
  ]
}