{
  "name": "FCollisionObjectQueryParams",
  "isStruct": true,
  "properties": {
    "ObjectTypesToQuery": [
      "int"
    ],
    "IgnoreMask": [
      "uint8"
    ]
  },
  "methods": [
    {
      "name": "AddObjectTypesToQuery",
      "return": "void",
      "args": [
        {
          "name": "QueryChannel",
          "type": "ECollisionChannel"
        }
      ]
    },
    {
      "name": "RemoveObjectTypesToQuery",
      "return": "void",
      "args": [
        {
          "name": "QueryChannel",
          "type": "ECollisionChannel"
        }
      ]
    },
    {
      "name": "GetQueryBitfield",
      "return": "int",
      "const": true,
      "args": []
    },
    {
      "name": "IsValid",
      "return": "bool",
      "const": true,
      "args": []
    },
    {
      "name": "DoVerify",
      "return": "void",
      "const": true,
      "args": []
    }
  ]
}