{
  "name": "FFloatArrayNormalizeDataflowNode",
  "isStruct": true,
  "doc": "Normalize the selected float data in a FloatArray",
  "properties": {
    "MinRange": [
      "float32",
      2,
      ""
    ],
    "MaxRange": [
      "float32",
      2,
      ""
    ],
    "bActive": [
      "bool",
      2,
      ""
    ]
  },
  "methods": [
    {
      "name": "opAssign",
      "return": "FFloatArrayNormalizeDataflowNode&",
      "args": [
        {
          "name": "Other",
          "type": "FFloatArrayNormalizeDataflowNode"
        }
      ]
    }
  ]
}