{
  "name": "FHeaderRowStyle",
  "isStruct": true,
  "doc": "Represents the appearance of an SHeaderRow",
  "properties": {
    "ColumnStyle": [
      "FTableColumnHeaderStyle",
      2,
      "Style of the normal header row columns"
    ],
    "LastColumnStyle": [
      "FTableColumnHeaderStyle",
      2,
      "Style of the last header row column"
    ],
    "ColumnSplitterStyle": [
      "FSplitterStyle",
      2,
      "Style of the splitter used between the columns"
    ],
    "SplitterHandleSize": [
      "float32",
      2,
      "Size of the splitter used between the columns"
    ],
    "BackgroundBrush": [
      "FSlateBrush",
      2,
      "Brush used to draw the header row background"
    ],
    "ForegroundColor": [
      "FSlateColor",
      2,
      "Color used to draw the header row foreground"
    ],
    "HorizontalSeparatorBrush": [
      "FSlateBrush",
      2,
      "Brush used to draw the splitter between the header and the contents below it"
    ],
    "HorizontalSeparatorThickness": [
      "float32",
      2,
      ""
    ]
  },
  "methods": [
    {
      "name": "opAssign",
      "return": "FHeaderRowStyle&",
      "args": [
        {
          "name": "Other",
          "type": "FHeaderRowStyle"
        }
      ]
    }
  ]
}