{
  "name": "FMetasoundFrontendClassName",
  "isStruct": true,
  "doc": "Name of a Metasound class",
  "properties": {
    "Namespace": [
      "FName",
      "Namespace of class."
    ],
    "Name": [
      "FName",
      "Name of class."
    ],
    "Variant": [
      "FName",
      "Variant of class. The Variant is used to describe an equivalent class which performs the same operation but on differing types."
    ]
  },
  "methods": [
    {
      "name": "opAssign",
      "return": "FMetasoundFrontendClassName&",
      "args": [
        {
          "name": "Other",
          "type": "FMetasoundFrontendClassName"
        }
      ]
    }
  ]
}