{
  "name": "FNiagaraDeviceProfileStateEntry",
  "isStruct": true,
  "properties": {
    "ProfileName": [
      "FName",
      2,
      ""
    ],
    "QualityLevelMask": [
      "uint",
      2,
      "The state of each set quality level."
    ],
    "SetQualityLevelMask": [
      "uint",
      2,
      "Which Effects Qualities are set."
    ]
  },
  "methods": [
    {
      "name": "opAssign",
      "return": "FNiagaraDeviceProfileStateEntry&",
      "args": [
        {
          "name": "Other",
          "type": "FNiagaraDeviceProfileStateEntry"
        }
      ]
    }
  ]
}