{
  "name": "FOnQuartzMetronomeEvent",
  "isStruct": true,
  "properties": {},
  "methods": [
    {
      "name": "opAssign",
      "return": "FOnQuartzMetronomeEvent&",
      "args": [
        {
          "name": "Other",
          "type": "FOnQuartzMetronomeEvent"
        }
      ]
    },
    {
      "name": "IsBound",
      "return": "bool",
      "const": true,
      "args": []
    },
    {
      "name": "Clear",
      "return": "void",
      "args": []
    },
    {
      "name": "AddUFunction",
      "return": "void",
      "args": [
        {
          "name": "Object",
          "type": "const UObject"
        },
        {
          "name": "FunctionName",
          "type": "FName"
        }
      ]
    },
    {
      "name": "Unbind",
      "return": "void",
      "args": [
        {
          "name": "Object",
          "type": "UObject"
        },
        {
          "name": "FunctionName",
          "type": "FName"
        }
      ]
    },
    {
      "name": "UnbindObject",
      "return": "void",
      "args": [
        {
          "name": "Object",
          "type": "UObject"
        }
      ]
    },
    {
      "name": "Broadcast",
      "return": "void",
      "const": true,
      "args": [
        {
          "name": "ClockName",
          "type": "FName"
        },
        {
          "name": "QuantizationType",
          "type": "EQuartzCommandQuantization"
        },
        {
          "name": "NumBars",
          "type": "int"
        },
        {
          "name": "Beat",
          "type": "int"
        },
        {
          "name": "BeatFraction",
          "type": "float32"
        }
      ]
    }
  ]
}