{
  "name": "FRigVMFunction_MathQuaternionMakeAbsolute",
  "isStruct": true,
  "doc": "Returns the absolute global transform within a parent's transform",
  "properties": {
    "Local": [
      "FQuat"
    ],
    "Parent": [
      "FQuat"
    ],
    "Global": [
      "FQuat",
      1,
      ""
    ]
  },
  "methods": [
    {
      "name": "opAssign",
      "return": "FRigVMFunction_MathQuaternionMakeAbsolute&",
      "args": [
        {
          "name": "Other",
          "type": "FRigVMFunction_MathQuaternionMakeAbsolute"
        }
      ]
    }
  ]
}