{
  "name": "UBlockAbilityTagsGameplayEffectComponent",
  "inherits": "UGameplayEffectComponent",
  "doc": "Handles blocking the activation of Gameplay Abilities based on Gameplay Tags for the Target actor of the owner Gameplay Effect",
  "properties": {
    "InheritableBlockedAbilityTagsContainer": [
      "FInheritedTagContainer",
      2,
      "These tags are applied to the target actor of the Gameplay Effect.  Blocked Ability Tags prevent Gameplay Abilities with these tags from executing."
    ]
  },
  "methods": []
}