{
  "name": "UGLTFMaterialExportOptions",
  "inherits": "UAssetUserData",
  "doc": "glTF-specific user data that can be added to material assets to override export options",
  "properties": {
    "Proxy": [
      "UMaterialInterface",
      "If assigned, export will use the proxy instead of the original material."
    ],
    "Default": [
      "FGLTFOverrideMaterialBakeSettings",
      "Default bake settings for this material in general."
    ],
    "Inputs": [
      "TMap<EGLTFMaterialPropertyGroup,FGLTFOverrideMaterialBakeSettings>",
      "Input-specific bake settings that override the defaults above."
    ]
  },
  "methods": []
}