{
  "name": "UNiagaraStatelessModule_SubUVAnimation",
  "inherits": "UNiagaraStatelessModule",
  "properties": {
    "NumFrames": [
      "int",
      2,
      ""
    ],
    "bStartFrameRangeOverride_Enabled": [
      "bool",
      2,
      ""
    ],
    "bEndFrameRangeOverride_Enabled": [
      "bool",
      2,
      ""
    ],
    "StartFrameRangeOverride": [
      "int",
      2,
      ""
    ],
    "EndFrameRangeOverride": [
      "int",
      2,
      ""
    ],
    "AnimationMode": [
      "ENSMSubUVAnimation_Mode",
      2,
      ""
    ],
    "LoopsPerSecond": [
      "float32",
      2,
      "-Note: Main module has PlaybackMode (Loops / FPS) to choose between loops or frames per second"
    ],
    "RandomChangeInterval": [
      "float32",
      2,
      "-Note: Main module has a few more options\nUPROPERTY(EditAnywhere, Category = \"Parameters\", meta = (EditConditionHides, EditCondition = \"AnimationMode == ENSMSubUVAnimation_Mode::Linear\"))\nbool bRandomStartFrame = false;\nint32 StartFrameOffset = 0;\nfloat LoopupIndexScale = 0.0f;"
    ]
  },
  "methods": []
}