{
  "name": "UScrollBar",
  "inherits": "UWidget",
  "properties": {
    "WidgetStyle": [
      "FScrollBarStyle",
      "Style of the scrollbar"
    ],
    "bAlwaysShowScrollbar": [
      "bool"
    ],
    "bAlwaysShowScrollbarTrack": [
      "bool"
    ],
    "Orientation": [
      "EOrientation"
    ],
    "Thickness": [
      "FVector2D",
      "The thickness of the scrollbar thumb"
    ],
    "Padding": [
      "FMargin",
      "The margin around the scrollbar"
    ]
  },
  "methods": [
    {
      "name": "SetState",
      "return": "void",
      "doc": "Set the offset and size of the track's thumb.\nNote that the maximum offset is 1.0-ThumbSizeFraction.\nIf the user can view 1/3 of the items in a single page, the maximum offset will be ~0.667f\n\n@param InOffsetFraction     Offset of the thumbnail from the top as a fraction of the total available scroll space.\n@param InThumbSizeFraction  Size of thumbnail as a fraction of the total available scroll space.",
      "ufunction": true,
      "meta": null,
      "args": [
        {
          "name": "InOffsetFraction",
          "type": "float32"
        },
        {
          "name": "InThumbSizeFraction",
          "type": "float32"
        }
      ]
    }
  ]
}